sphinx_syft_theme/__init__.py
sphinx_syft_theme/_compile_translations.py
sphinx_syft_theme/assets/images/download.rng
sphinx_syft_theme/assets/images/download.svg
sphinx_syft_theme/assets/images/fullscreen.rng
sphinx_syft_theme/assets/images/fullscreen.svg
sphinx_syft_theme/assets/images/theme-sun.rng
sphinx_syft_theme/assets/images/theme-sun.svg
sphinx_syft_theme/assets/scripts/bootstrap.js
sphinx_syft_theme/assets/scripts/header-buttons.js
sphinx_syft_theme/assets/scripts/mixin.js
sphinx_syft_theme/assets/scripts/sphinx-syft-theme.js
sphinx_syft_theme/assets/styles/abstracts/_accessibility.scss
sphinx_syft_theme/assets/styles/abstracts/_all.scss
sphinx_syft_theme/assets/styles/abstracts/_color.scss
sphinx_syft_theme/assets/styles/abstracts/_links.scss
sphinx_syft_theme/assets/styles/abstracts/_mixins.scss
sphinx_syft_theme/assets/styles/base/_base.scss
sphinx_syft_theme/assets/styles/bootstrap.scss
sphinx_syft_theme/assets/styles/components/_breadcrumbs.scss
sphinx_syft_theme/assets/styles/components/_feedback.scss
sphinx_syft_theme/assets/styles/components/_icon-links.scss
sphinx_syft_theme/assets/styles/components/_indices.scss
sphinx_syft_theme/assets/styles/components/_navbar-links.scss
sphinx_syft_theme/assets/styles/components/_page-toc.scss
sphinx_syft_theme/assets/styles/components/_prev-next.scss
sphinx_syft_theme/assets/styles/components/_readthedocs-switcher.scss
sphinx_syft_theme/assets/styles/components/_search.scss
sphinx_syft_theme/assets/styles/components/_searchbox.scss
sphinx_syft_theme/assets/styles/components/_switcher-theme.scss
sphinx_syft_theme/assets/styles/components/_switcher-version.scss
sphinx_syft_theme/assets/styles/components/_text-links.scss
sphinx_syft_theme/assets/styles/components/_toc-inpage.scss
sphinx_syft_theme/assets/styles/components/_versionmodified.scss
sphinx_syft_theme/assets/styles/components/header/_header-logo.scss
sphinx_syft_theme/assets/styles/content/_admonitions.scss
sphinx_syft_theme-0.3.4.dist-info/LICENSE
sphinx_syft_theme-0.3.4.dist-info/METADATA
sphinx_syft_theme-0.3.4.dist-info/WHEEL
sphinx_syft_theme-0.3.4.dist-info/entry_points.txt
sphinx_syft_theme-0.3.4.dist-info/RECORD