Metadata-Version: 2.1
Name: sphinx-syft-theme
Version: 0.3.4
Summary: Bootstrap-based Sphinx theme from the syft community
Author-Email: Callis Ezenwaka <callisezenwaka@gmail.com>
Maintainer-Email: Callis Ezenwaka <callisezenwaka@gmail.com>
License:                                Apache License
Classifier: Development Status :: 5 - Production/Stable
Classifier: Programming Language :: Python :: 3
Classifier: Programming Language :: Python :: 3.9
Classifier: Programming Language :: Python :: 3.10
Classifier: Programming Language :: Python :: 3.11
Classifier: Programming Language :: Python :: 3.12
Classifier: Framework :: Sphinx
Classifier: Framework :: Sphinx :: Theme
Classifier: License :: OSI Approved :: BSD License
Classifier: Operating System :: OS Independent
Project-URL: Homepage, https://sphinx-syft-theme.readthedocs.io/
Project-URL: Documentation, https://sphinx-syft-theme.readthedocs.io/
Project-URL: Repository, https://github.com/callezenwaka/sphinx-syft-theme
Project-URL: Changelog, https://sphinx-syft-theme.readthedocs.io/en/latest/changelog.html
Requires-Python: >=3.10
Requires-Dist: sphinx>=5
Requires-Dist: beautifulsoup4
Requires-Dist: docutils!=0.17.0
Requires-Dist: Babel
Requires-Dist: pygments>=2.7
Requires-Dist: accessible-pygments
Requires-Dist: typing-extensions
Requires-Dist: numpydoc; extra == "doc"
Requires-Dist: linkify-it-py; extra == "doc"
Requires-Dist: rich; extra == "doc"
Requires-Dist: sphinxext-rediraffe; extra == "doc"
Requires-Dist: sphinx-sitemap; extra == "doc"
Requires-Dist: sphinx-autoapi>=3.0.0; extra == "doc"
Requires-Dist: myst-parser; extra == "doc"
Requires-Dist: ablog>=0.11.8; extra == "doc"
Requires-Dist: jupyter_sphinx; extra == "doc"
Requires-Dist: pandas; extra == "doc"
Requires-Dist: plotly; extra == "doc"
Requires-Dist: matplotlib; extra == "doc"
Requires-Dist: numpy; extra == "doc"
Requires-Dist: xarray; extra == "doc"
Requires-Dist: sphinx_click; extra == "doc"
Requires-Dist: sphinx-copybutton; extra == "doc"
Requires-Dist: sphinx-design; extra == "doc"
Requires-Dist: sphinx_comments; extra == "doc"
Requires-Dist: sphinx-togglebutton; extra == "doc"
Requires-Dist: sphinx_external_toc; extra == "doc"
Requires-Dist: sphinx-tabs; extra == "doc"
Requires-Dist: sphinx_thebe; extra == "doc"
Requires-Dist: sphinxcontrib-bibtex; extra == "doc"
Requires-Dist: sphinxext-opengraph; extra == "doc"
Requires-Dist: jupyterlite-sphinx; extra == "doc"
Requires-Dist: sphinxcontrib-youtube>=1.4.1; extra == "doc"
Requires-Dist: sphinx-favicon>=1.0.1; extra == "doc"
Requires-Dist: ipykernel; extra == "doc"
Requires-Dist: nbsphinx; extra == "doc"
Requires-Dist: ipyleaflet; extra == "doc"
Requires-Dist: colorama; extra == "doc"
Requires-Dist: ipywidgets; extra == "doc"
Requires-Dist: graphviz; extra == "doc"
Requires-Dist: myst_nb; extra == "doc"
Requires-Dist: pytest; extra == "test"
Requires-Dist: pytest-cov; extra == "test"
Requires-Dist: pytest-regressions; extra == "test"
Requires-Dist: sphinx[test]; extra == "test"
Requires-Dist: pyyaml; extra == "dev"
Requires-Dist: pre-commit; extra == "dev"
Requires-Dist: sphinx-syft-theme[doc,test]; extra == "dev"
Requires-Dist: tox; extra == "dev"
Requires-Dist: pandoc; extra == "dev"
Requires-Dist: sphinx-theme-builder[cli]; extra == "dev"
Requires-Dist: pytest-playwright; extra == "a11y"
Requires-Dist: Babel; extra == "i18n"
Requires-Dist: jinja2; extra == "i18n"
Provides-Extra: doc
Provides-Extra: test
Provides-Extra: dev
Provides-Extra: a11y
Provides-Extra: i18n
